__init__.py
parser.py
setup.cfg
setup.py
validator.py
configbuilder.egg-info/PKG-INFO
configbuilder.egg-info/SOURCES.txt
configbuilder.egg-info/dependency_links.txt
configbuilder.egg-info/requires.txt
configbuilder.egg-info/top_level.txt