Metadata-Version: 1.0
Name: configbuilder
Version: 0.1
Summary: General purpose configuration parser builder
Home-page: https://github.com/joongh/configbuilder
Author: Joong-Hee Lee
Author-email: leejoonghee@gmail.com
License: MIT
Platform: UNKNOWN
